{
  "number": "ST8-09",
  "colors": [
    "Blue"
  ],
  "rarity": "R",
  "card_type": "Digimon",
  "level": "6",
  "name": "Slayerdramon",
  "form": "Mega",
  "attribute": "Vaccine",
  "type": "Dragonkin",
  "dp": "11000",
  "play_cost": "11",
  "digivolves": [
    {
      "level": "5",
      "cost": "3",
      "color": "Blue"
    }
  ],
  "effect": "[When Digivolving] This Digimon gains ＜Security Attack +1＞ for the turn. (This Digimon checks 1 additional security card.)[Your Turn] This Digimon is unblockable."
}